Workbook
Name aporte: Plan1!#REF!
Name patrimonio: Plan1!$D$22
Name qtd_anos: Plan1!$D$20
Name Rendimento: Plan1!$C$11
Name rendimento_carteira: Plan1!$D$15
Name Salario: Plan1!$B$11
Name Sugestao_investimento: Plan1!$D$11
Name taxa_mensal: Plan1!$D$21

Sheet Plan1
B9: CONFIGURAÇÕES
B10: Salário | C10: Rendimento Carteira | D10: Sugestão de Investimento (30%)
B11: 2000 | C11: 0.006 | D11: =B11*30% -> 600
B13: INVESTIMENTO MENSAL
B14: Quanto investir por mês ? | D14: 200
B15: Por Quantos Anos ? | D15: 5
B16: Taxa de Rendimento mensal ? | D16: 0.01079
B17: Patrimônio acumulado ? | D17: =FV(D16,D15*12,D14*-1) -> 16755.383
B18: Dividendos Mensais ? | D18: =D17*C11 -> 100.5323
B20: Cenários | D20: Dividendo
A21: 2 | B21: Quanto em 2 Anos ? | C21: =FV($D$16,$A21*12,$D$14*-1) -> 5445.5255 | D21: =C21*$C$11 -> 32.673153
A22: 5 | B22: Quanto em 5 Anos ? | C22: =FV($D$16,$A22*12,$D$14*-1) -> 16755.383 | D22: =C22*$C$11 -> 100.5323
A23: 10 | B23: Quanto em 10 Anos ? | C23: =FV($D$16,$A23*12,$D$14*-1) -> 48656.843 | D23: =C23*$C$11 -> 291.94106
A24: 20 | B24: Quanto em 20 Anos ? | C24: =FV($D$16,$A24*12,$D$14*-1) -> 225039.68 | D24: =C24*$C$11 -> 1350.2381
A25: 30 | B25: Quanto em 30 Anos ? | C25: =FV($D$16,$A25*12,$D$14*-1) -> 864433.93 | D25: =C25*$C$11 -> 5186.6036
B28: PERFIL | D28: Moderado
B29: Valor a ser investido por mês | D29: =D14 -> 200
B31: TIPO DE FII | C31: Percentual Sugerido | D31: Valores
B32: PAPEL | C32: =VLOOKUP($D$28&"-"&B32,Plan2!$B:$E,4,0) -> 0.32 | D32: =C32*$D$29 -> 64
B33: TIJOLO | C33: =VLOOKUP($D$28&"-"&B33,Plan2!$B:$E,4,0) -> 0.35 | D33: =C33*$D$29 -> 70
B34: HÍBRIDOS | C34: =VLOOKUP($D$28&"-"&B34,Plan2!$B:$E,4,0) -> 0.08 | D34: =C34*$D$29 -> 16
B35: FOFs | C35: =VLOOKUP($D$28&"-"&B35,Plan2!$B:$E,4,0) -> 0.05 | D35: =C35*$D$29 -> 10
B36: DESENVOLVIMENTO | C36: =VLOOKUP($D$28&"-"&B36,Plan2!$B:$E,4,0) -> 0.1 | D36: =C36*$D$29 -> 20
B37: HOTELARIAS | C37: =VLOOKUP($D$28&"-"&B37,Plan2!$B:$E,4,0) -> 0.1 | D37: =C37*$D$29 -> 20
D38: =SUM(D32:D37) -> 200

Sheet Plan2
B3: CHAVE | C3: PERFIL | D3: TIPO DE FII | E3: %
B4: =C4&"-"&D4 -> Conservador-PAPEL | C4: Conservador | D4: PAPEL | E4: 0.3
B5: =C5&"-"&D5 -> Conservador-TIJOLO | C5: Conservador | D5: TIJOLO | E5: 0.5
B6: =C6&"-"&D6 -> Conservador-HÍBRIDOS | C6: Conservador | D6: HÍBRIDOS | E6: 0.1
B7: =C7&"-"&D7 -> Conservador-FOFs | C7: Conservador | D7: FOFs | E7: 0.1
B8: =C8&"-"&D8 -> Conservador-DESENVOLVIMENTO | C8: Conservador | D8: DESENVOLVIMENTO | E8: 0
B9: =C9&"-"&D9 -> Conservador-HOTELARIAS | C9: Conservador | D9: HOTELARIAS | E9: 0
B10: =C10&"-"&D10 -> Moderado-PAPEL | C10: Moderado | D10: PAPEL | E10: 0.32
B11: =C11&"-"&D11 -> Moderado-TIJOLO | C11: Moderado | D11: TIJOLO | E11: 0.35
B12: =C12&"-"&D12 -> Moderado-HÍBRIDOS | C12: Moderado | D12: HÍBRIDOS | E12: 0.08
B13: =C13&"-"&D13 -> Moderado-FOFs | C13: Moderado | D13: FOFs | E13: 0.05
B14: =C14&"-"&D14 -> Moderado-DESENVOLVIMENTO | C14: Moderado | D14: DESENVOLVIMENTO | E14: 0.1
B15: =C15&"-"&D15 -> Moderado-HOTELARIAS | C15: Moderado | D15: HOTELARIAS | E15: 0.1
... B21: =C21&"-"&D21 -> Agressivo-HOTELARIAS | C21: Agressivo | D21: HOTELARIAS | E21: 0.1

Sheet Plan3
